bbw/__init__.py
bbw/bbw.py
bbw-0.1.2.data/scripts/bbw_cli.py
bbw-0.1.2.data/scripts/bbw_gui.py
bbw-0.1.2.data/scripts/bbw_parallel.sh
bbw-0.1.2.dist-info/LICENSE
bbw-0.1.2.dist-info/METADATA
bbw-0.1.2.dist-info/WHEEL
bbw-0.1.2.dist-info/top_level.txt
bbw-0.1.2.dist-info/RECORD
