Metadata-Version: 2.1
Name: bbw
Version: 0.1.2
Summary: Library for semantic annotation of tabular data with the Wikidata knowledge graph
Home-page: https://github.com/UB-Mannheim/bbw
Author: Renat Shigapov, Philipp Zumstein, Jan Kamlah, Lars Oberlaender, Joerg Mechnich, Irene Schumm
License: MIT
Platform: UNKNOWN
Classifier: License :: OSI Approved :: MIT License
Classifier: Intended Audience :: Developers
Classifier: Intended Audience :: Education
Classifier: Intended Audience :: Science/Research
Classifier: Operating System :: OS Independent
Classifier: Programming Language :: Python
Classifier: Programming Language :: Python :: 3
Classifier: Programming Language :: Python :: 3.6
Classifier: Programming Language :: Python :: 3.7
Classifier: Programming Language :: Python :: 3.8
Classifier: Topic :: Software Development :: Libraries
Classifier: Topic :: Software Development :: Libraries :: Python Modules
Requires-Python: >=3.6
Requires-Dist: ftfy (>=5.8)
Requires-Dist: tqdm (>=4.48.0)
Requires-Dist: pandas (>=1.0.5)
Requires-Dist: streamlit (>=0.70.0)
Requires-Dist: requests (>=2.23.0)
Requires-Dist: numpy (>=1.18.4)
Requires-Dist: beautifulsoup4 (>=4.9.3)
Requires-Dist: langid (>=1.1.6)
